dame/__init__.py
dame/__main__.py
dame/_utils.py
dame/cli_methods.py
dame/configuration.py
dame/cwl.py
dame/downloader.py
dame/executor.py
dame/local_file_manager.py
dame/modelcatalogapi.py
dame/utils.py
dame/transformations/topoflow_climate.yml
dame_cli-5.8.0.dist-info/LICENSE
dame_cli-5.8.0.dist-info/METADATA
dame_cli-5.8.0.dist-info/WHEEL
dame_cli-5.8.0.dist-info/entry_points.txt
dame_cli-5.8.0.dist-info/top_level.txt
dame_cli-5.8.0.dist-info/RECORD
