Metadata-Version: 2.1
Name: dame-cli
Version: 5.8.0
Summary: A execution manager cli for execution
Home-page: https://github.com/mintproject/dame_cli
Author: Maximiliano Osorio
Author-email: mosorio@isi.edu
License: Apache-2
Platform: UNKNOWN
Classifier: License :: OSI Approved :: Apache Software License
Classifier: Development Status :: 3 - Alpha
Classifier: Programming Language :: Python
Classifier: Programming Language :: Python :: 3
Classifier: Programming Language :: Python :: 3.5
Classifier: Programming Language :: Python :: 3.6
Classifier: Programming Language :: Python :: 3.7
Classifier: Intended Audience :: Science/Research
Classifier: Operating System :: Unix
Requires-Python: >=3.6.0
Requires-Dist: click (==7.1.2)
Requires-Dist: decorator (==4.4.2)
Requires-Dist: networkx (==2.5.1)
Requires-Dist: modelcatalog-api (==8.0.0)
Requires-Dist: texttable (==1.6.3)
Requires-Dist: validators (==0.18.1)
Requires-Dist: PyYAML (==5.4)
Requires-Dist: semver (==2.10.2)
Requires-Dist: requests (>=2.24.0)
Requires-Dist: jsonschema (==3.2.0)
Requires-Dist: configparser (==5.0.1)
Requires-Dist: certifi (==2020.6.20)
Requires-Dist: docker (==4.3.1)
Requires-Dist: urllib3 (==1.24.2)
